{
  "id": "646905861",
  "title": "PJ開始前の事前情報サマリー（システム情報以外）",
  "content": "塾講師ステーションの現状 登録社数：2,000社（学習塾） 月間PV 100〜200万PVくらい 稼働のピークは2〜5月 現行ベンダー： https://appirits.com/ 現状の言語：Ruby on Rails（Ruby 1.8.7 / Rails 2.3.18） 基本PCはChrome、Edge、iOSはSafariのみ対象にしており, Androidはテストしていない。 ランニング費用 保守：改修依頼しない場合、月14万（問合せ、緊急対応） AWS費用：月20-30万（平均約22万） 改善：固定で１人月程度（セキュリティや、バージョンUP対応含む） リニューアルについて 要望・懸念など リリース時期 6月に固定したい。学生の波に影響しないタイミング。 表示速度改善したい ブラウザ：EdgeはFirefoxより少ないので不要かも。要件定義フェーズで見極める。 ディレクトリ構造変える場合（これまで蓄積してきた）SEOへの影響が心配 &rarr;ディレクトリ構造は変えないつもり。URL構造は長いのでリダイレクトで調整したい。URL構造で固定URLとSearch結果のURLで分散してしまっているが、方向性はまとめておく（2022/10/14 池田様） UIは大きく考えることは考えていない。求人情報の入れ替えなどは考えているが、現状ベース。（2022/10/14 池田様） 所々にある裏機能（例：口コミ評価を検索アルゴリズムに入れている、や、管理系など）がリニューアルで落とされないか。 希望変更箇所 クライアント側でお祝いの金額変更を可能にする。それに伴う採用単価の設定機能など。ゼロから作る機能 アルバイト版とキャリア版の求人管理ページが１つになってしまっている。今回分けられたら良い。マスタを分けたり、管理画面も分けないが、見せ方として２つが分けて見える様にしたい。資料にまとめる。（2022/10/14 鈴木様・原口様） プロジェクト進行について ツールはSlack（connectは使えないのでゲスト招待）、Jira、Confluence、bitbucketでOK インフラ面で、現行ベンダーへもトモノカイ様経由で質問可能 トモノカイ様による作業（GIG想定） 要求・要件定義 情報提供 100-150Pほどのご要件定義書やWF全要素を確認いただく稼働が必要になる。 デザイン １Pずつ確認するかはご希望次第 開発 機能はある程度のまとまり単位で都度、ご確認いただく必要あり。リリース前のUAT。 データ移行 計画立案時・移行実施時にも、現状のデータ集約やサーバ設定や利用者への案内などでトモノカイ様作業発生する。 納品 DVDに焼くなどは求めない。ソースコードの確認もしておらず、サイトの環境に反映されていれば良い。（2022/10/14 鈴木） 契約 GIGが以前から保有していたものは、個別契約にて明示必要 リニューアル後の保守 GIG想定 アプリ、サーバ保守：月40〜50万円 改善：月100-150万程度（内容による） AWS：15-20万程度（アクセス数やセキュリティレベルによる）",
  "parentId": "643858450",
  "parentTitle": "塾講師ステーションドキュメントスペース",
  "labels": [],
  "url": "/spaces/CLIENTTOMO/pages/646905861/PJ",
  "spaceKey": "CLIENTTOMO",
  "lastModified": "2022-12-12T03:38:54.202Z",
  "author": "ejiri_yusuke",
  "excerpt": "塾講師ステーションの現状 登録社数：2,000社（学習塾） 月間PV 100〜200万PVくらい 稼働のピークは2〜5月 現行ベンダー： https://appirits.com/ 現状の言語：Ruby on Rails（Ruby 1.8.7 / Rails 2.3.18） 基本PCはChrome、Edge、iOSはSafariのみ対象にしており, Androidはテストしていない。 ランニング費..."
}