{
  "id": "854294586",
  "title": "2023-10-04 ミーティング議事録",
  "content": "&nbsp;日付 &nbsp;参加者 トモノカイ：鈴木様( )、池田様( ) GIG： 資料 スケジュール タスク管理（Jira） &nbsp;議題 項目 プレゼンター メモ 進捗確認 トモノカイ社の受け入れテスト 教室グループ管理のテストはほぼ終了 不要な機能などの調整をGIGで対応 TOP検索モーダルのコメント確認 SP版に限り、都道府県までしか表示しない（市区町村は表示しない）、また路線も都道府県までしか表示しない。&rarr;つまりエリア／路線の区切りをなくす。 会員登録機能のWF/デザイン補足説明 学年に入学見込みを入れた点&rarr;OK 入学年の注釈は不要なため削除した点&rarr;OK ログの保存期間：1ヶ月間を想定&rarr;OK 会員情報、特にオファー関連で新たに登録したい項目がある。 オファーを受ける際に希望する指導形態、職種や勤務希望地を会員の帳票に追加し持たせたい トモノカイ様がチケットを作成予定 求人詳細はトモノカイ様はチェック済み、SEO会社のチェックが今週中にある &nbsp;アクション事項 15 incomplete &nbsp;決定事項 「/decision」と入力してこのミーティングで決定した内容を記録します。: b9455583-fc11-4f6e-a694-f0f5e364eda8 7113baef-b9fe-4a11-a28f-9518f6a1b72a DECIDED",
  "parentId": "1235746832",
  "parentTitle": "議事録_2023年",
  "labels": [],
  "url": "/spaces/CLIENTTOMO/pages/854294586/2023-10-04",
  "spaceKey": "CLIENTTOMO",
  "lastModified": "2023-10-04T06:49:32.170Z",
  "author": "元ユーザー (Deleted)",
  "excerpt": "&nbsp;日付 &nbsp;参加者 トモノカイ：鈴木様( )、池田様( ) GIG： 資料 スケジュール タスク管理（Jira） &nbsp;議題 項目 プレゼンター メモ 進捗確認 トモノカイ社の受け入れテスト 教室グループ管理のテストはほぼ終了 不要な機能などの調整をGIGで対応 TOP検索モーダルのコメント確認 SP版に限り、都道府県までしか表示しない（市区町村は表示しない）、また路線も都..."
}