{
  "id": "1405780109",
  "title": "2025-03-05 ミーティング議事録",
  "content": "&nbsp;日付 ==15:30終了想定で進行いたします=== &nbsp;参加者 トモノカイ：池田様( )、片岡様（ ）、原口様 GIG： 資料 スケジュール タスク管理（Jira） &nbsp;議題 項目 プレゼンター メモ 前回のネクストアクションの確認 16 16 incomplete STG環境停止のスケジュールを検討し進める 17 17 incomplete スケジュールが確定次第ご連絡いたします。 18 18 incomplete 外形監視をDEVと本番を対象にする 19 19 incomplete 覚書でSTGからDEVに変更する 20 20 incomplete 覚書の内容をトモノカイ様確認中 21 21 complete [済] 外形監視の対象をDEVにする 22 22 complete こちらは先立って対応済みになります 23 23 complete CTJ-4962 0f376871-0459-35fc-b139-2a34c915ec22 System Jira については仕様検討を進める 24 24 complete 弊社対応進行中 進捗確認 dev環境で弊社確認中のチケット：工数管理表で緑色の背景になっているチケット 今週木曜日に反映予定のチケット DEVトモノカイ様検証OKのチケット そのほか トモノカイ様社内からのアクセスの際にサービスサイト、クライアント画面にて下記のようなエラーが確認される事象について（GIG小竹） 現状わかっていること（他の時間帯でも発生している可能性あり） 発生時刻：3/4(火)11:46 アクセスページ：情報局TOP、サイトTOP 調査結果 トモノカイ様社内からのアクセスのみで上記の事象が発生していると思われるため該当時間帯でのアクセスログの特定を進め、原因を調査する 結論、移転先のIPアドレス（182.169.82.19）がWAFのrate limitに引っかかっているため 60秒間で50アクセスの制限に引っかかっている ratelimitの設定で、GIGとトモノカイさんのIPの除外設定をしていたが、オフィスの変更により除外すべきIPに追加されていなかった 今後の対応 上記IPはWAFの制限から外す -&gt;対応する トモノカイ様へのご依頼 上記事象の対応の優先度を決めるためにチケットの起票および工数管理表への記載をお願いいたします。-&gt;無視 フェーズ5は昨日の本番反映によりリリース完了いたしました。 引き続き、改善フェーズの対応進めてまいります。 よろしくお願いいたします。 &nbsp;アクション事項 25 25 incomplete STG環境停止対応の進行 26 26 complete WAFのIP制限からトモノカイ新本社IPを除外する。 &nbsp;決定事項 「/decision」と入力してこのミーティングで決定した内容を記録します。: b9455583-fc11-4f6e-a694-f0f5e364eda8 7113baef-b9fe-4a11-a28f-9518f6a1b72a DECIDED",
  "parentId": "1710817285",
  "parentTitle": "議事録_2025年",
  "labels": [],
  "url": "/spaces/CLIENTTOMO/pages/1405780109/2025-03-05",
  "spaceKey": "CLIENTTOMO",
  "lastModified": "2025-03-05T07:27:25.101Z",
  "author": "kotake_jin",
  "excerpt": "&nbsp;日付 ==15:30終了想定で進行いたします=== &nbsp;参加者 トモノカイ：池田様( )、片岡様（ ）、原口様 GIG： 資料 スケジュール タスク管理（Jira） &nbsp;議題 項目 プレゼンター メモ 前回のネクストアクションの確認 16 16 incomplete STG環境停止のスケジュールを検討し進める 17 17 incomplete スケジュールが確定次第ご連..."
}